app/__init__.py
app/main.py
config/__init__.py
config/auth.json
config/breach_apis.json
config/leak_sources.json
config/progress_bar_config.json
config/tor_config.json
olhodedeus/__init__.py
olhodedeus/__main__.py
olhodedeus/auth.py
olhodedeus/cli.py
olhodedeus/core.py
olhodedeus/sync.py
pipeline/__init__.py
pipeline/decrypt_search.py
pipeline/extractors.py
pipeline/ingest.py
pipeline/search.py
pipeline/utils.py
scraper/__init__.py
scraper/downloader.py
tools/Gen_And_Checkers.py
tools/api/__init__.py
tools/api/api_server.py
tools/automation/__init__.py
tools/automation/credential_manager.py
tools/automation/dashboard.py
tools/automation/recon_automation.py
tools/automation/report_generator.py
tools/automation/scheduler.py
tools/defense/__init__.py
tools/defense/firewall_generator.py
tools/defense/log_analyzer.py
tools/defense/malware_analyzer.py
tools/defense/network_traffic.py
tools/defense/ransomware_db.py
tools/ingest/README.md
tools/ingest/README_EXTRA.md
tools/ingest/allowed_sources.json
tools/ingest/analyze.py
tools/ingest/breach_sources.py
tools/ingest/darkweb_access.py
tools/ingest/decrypt_and_search.py
tools/ingest/extractors.py
tools/ingest/hash_cracker.py
tools/ingest/ingest_categorize.py
tools/ingest/ingest_hibp.py
tools/ingest/leak_sources.py
tools/ingest/osint_tools.py
tools/ingest/paste_monitor.py
tools/ingest/pipeline.py
tools/ingest/scraper.py
tools/ingest/search.py
tools/ingest/utils.py
tools/ingest/watch_and_ingest.py
tools/offensive/__init__.py
tools/offensive/banner_grabber.py
tools/offensive/c2_lite.py
tools/offensive/dns_toolkit.py
tools/offensive/exploit_db.py
tools/offensive/payload_generator.py
tools/offensive/port_scanner.py
tools/offensive/service_enum.py
tools/offensive/stress_tester.py
tools/offensive/waf_detector.py
tools/offensive/web_fuzzer.py
tools/osint_advanced/__init__.py
tools/osint_advanced/company_osint_br.py
tools/osint_advanced/darkweb_monitor.py
tools/osint_advanced/email_hunter.py
tools/osint_advanced/face_recognition.py
olhodedeus-1.2.0.dist-info/METADATA
olhodedeus-1.2.0.dist-info/WHEEL
olhodedeus-1.2.0.dist-info/entry_points.txt
olhodedeus-1.2.0.dist-info/top_level.txt
olhodedeus-1.2.0.dist-info/RECORD
