Metadata-Version: 2.4
Name: olhodedeus
Version: 1.2.0
Summary: 🔍 Olho de Deus - Ferramenta OSINT e análise de segurança
Author-email: Olho de Deus Team <contato@olhodedeus.dev>
License: MIT
Project-URL: Homepage, https://github.com/olhodedeus/olhodedeus
Project-URL: Documentation, https://github.com/olhodedeus/olhodedeus#readme
Project-URL: Repository, https://github.com/olhodedeus/olhodedeus
Project-URL: Issues, https://github.com/olhodedeus/olhodedeus/issues
Keywords: osint,security,recon,leak-checker,pentest
Classifier: Development Status :: 4 - Beta
Classifier: Environment :: Console
Classifier: Intended Audience :: Developers
Classifier: Intended Audience :: Information Technology
Classifier: License :: OSI Approved :: MIT License
Classifier: Operating System :: OS Independent
Classifier: Programming Language :: Python :: 3
Classifier: Programming Language :: Python :: 3.10
Classifier: Programming Language :: Python :: 3.11
Classifier: Programming Language :: Python :: 3.12
Classifier: Programming Language :: Python :: 3.13
Classifier: Topic :: Security
Classifier: Topic :: Internet
Requires-Python: >=3.10
Requires-Dist: requests>=2.28.0
Requires-Dist: colorama>=0.4.6
Requires-Dist: rich>=13.0.0
Requires-Dist: click>=8.1.0
Requires-Dist: python-whois>=0.8.0
Requires-Dist: dnspython>=2.3.0
Requires-Dist: shodan>=1.28.0
Requires-Dist: beautifulsoup4>=4.12.0
Requires-Dist: lxml>=4.9.0
Requires-Dist: pysocks>=1.7.1
Requires-Dist: cryptography>=41.0.0
Requires-Dist: python-gnupg>=0.5.0
Requires-Dist: tqdm>=4.65.0
Provides-Extra: dev
Requires-Dist: pytest>=7.0.0; extra == "dev"
Requires-Dist: black>=23.0.0; extra == "dev"
Requires-Dist: flake8>=6.0.0; extra == "dev"
Provides-Extra: full
Requires-Dist: discord-webhook>=1.0.0; extra == "full"
Requires-Dist: numpy>=1.24.0; extra == "full"
Requires-Dist: phonenumbers>=8.13.0; extra == "full"
